{
    "data_id": "33",
    "type": "bound",
    "problem": "Let $a, b, c$ be positive real numbers such that $a + b + c = 1$. Find the largest constant $C$ such that the following inequality holds for all $a, b, c$:\n$$\n\\sqrt{\\frac{1}{a}-1} \\sqrt{\\frac{1}{b}-1} + \\sqrt{\\frac{1}{b}-1} \\sqrt{\\frac{1}{c}-1} + \\sqrt{\\frac{1}{c}-1} \\sqrt{\\frac{1}{a}-1} \\geq C\n$$",
    "current_solution": "Let $a=x y, b=y z, c=z x$. Then $x y+y z+z x=1$ and we may take\n$$\nx=\\tan \\frac{\\alpha}{2}, \\quad y=\\tan \\frac{\\beta}{2}, \\quad z=\\tan \\frac{\\gamma}{2}\n$$\nwhere $\\alpha, \\beta, \\gamma \\in(0, \\pi)$ and $\\alpha+\\beta+\\gamma=\\pi$.\nWe have\n$$\n\\begin{aligned}\n\\sqrt{\\frac{1}{a}-1} \\sqrt{\\frac{1}{b}-1} & =\\sqrt{\\frac{(1-a)(1-b)}{a b}}=\\sqrt{\\frac{(1-x y)(1-y z)}{x y^{2} z}} \\\\\n& =\\sqrt{\\frac{(y z+z x)(z x+x y)}{x y^{2} z}}=\\sqrt{\\frac{(y+x)(z+y)}{y^{2}}}=\\frac{\\sqrt{1+y^{2}}}{y} \\\\\n& =\\frac{\\sqrt{1+\\tan ^{2} \\frac{\\beta}{2}}}{\\tan \\frac{\\beta}{2}}=\\frac{1}{\\sin \\frac{\\beta}{2}}\n\\end{aligned}\n$$\n\nSimilarly we obtain\n$$\n\\sqrt{\\frac{1}{b}-1} \\sqrt{\\frac{1}{c}-1}=\\frac{1}{\\sin \\frac{\\gamma}{2}} \\quad \\text { and } \\quad \\sqrt{\\frac{1}{c}-1} \\sqrt{\\frac{1}{a}-1}=\\frac{1}{\\sin \\frac{\\alpha}{2}}\n$$\n\nNow the given inequality becomes\n$$\n\\frac{1}{\\sin \\frac{\\alpha}{2}}+\\frac{1}{\\sin \\frac{\\beta}{2}}+\\frac{1}{\\sin \\frac{\\gamma}{2}} \\geq 6\n$$\n\nBy $A M \\geq H M$ we have\n$$\n\\frac{1}{\\sin \\frac{\\alpha}{2}}+\\frac{1}{\\sin \\frac{\\beta}{2}}+\\frac{1}{\\sin \\frac{\\gamma}{2}} \\geq \\frac{9}{\\sin \\frac{\\alpha}{2}+\\sin \\frac{\\beta}{2}+\\sin \\frac{\\gamma}{2}}\n$$\n\nSo we need to prove that $\\sin \\frac{\\alpha}{2}+\\sin \\frac{\\beta}{2}+\\sin \\frac{\\gamma}{2} \\leq \\frac{3}{2}$.\n\nEquality occurs if and only if $\\alpha=\\beta=\\gamma=\\pi / 3$, i.e. $a=b=c=\\frac{1}{3}$. In this case, the minimum value of the expression is achieved, so $C = 6$ is the largest constant for which the inequality always holds.\n\nTherefore, the answer is $C = 6$.",
    "answer": "$C = 6$",
    "enhanced_solution": "Enhanced Solution:\n\nWe wish to prove that for all positive real numbers a,b,c satisfying a+b+c=1,\n\n    √\\bigl(1/a−1\\bigr)·√\\bigl(1/b−1\\bigr) + √\\bigl(1/b−1\\bigr)·√\\bigl(1/c−1\\bigr) + √\\bigl(1/c−1\\bigr)·√\\bigl(1/a−1\\bigr) ≥ C,\n\nand to determine the largest possible constant C.  The given solution proceeds by a symmetric substitution and then reduces the problem to an inequality in the half‐angles of a triangle.  We now present a more detailed and rigorous version of that argument, preserving the same solution strategy and final answer.\n\n1. Substitution a=xy, b=yz, c=zx.  \n   Since a,b,c>0 and a+b+c=1, we may introduce positive reals x,y,z so that\n\n       a = x y,\n       b = y z,\n       c = z x,\n\n   and consequently\n\n       a+b+c = x y + y z + z x = 1.                       (1)\n\n   This parametrization is standard in symmetric problems of three positive variables under the constraint a+b+c=1.\n\n2. Rewriting each term.  \n   We examine one generic term:\n\n       √\\bigl(1/a − 1\\bigr) · √\\bigl(1/b − 1\\bigr)\n       = √\\frac{(1−a)(1−b)}{a b}.\n\n   Using 1−a = b+c = y z + z x and 1−b = c+a = z x + x y, we get\n\n       (1−a)(1−b) = (y z + z x)(z x + x y)\n                   = z(y+ x) · x(z+ y)\n                   = x z · (x+y)(y+z).\n\n   Meanwhile, a b = (x y)(y z) = x y^2 z.  Hence\n\n       √\\frac{(1−a)(1−b)}{a b}\n       = √\\frac{x z · (x+y)(y+z)}{x y^2 z}\n       = √\\frac{(x+y)(y+z)}{y^2}.\n\n   But from (1) we have x y + y z + z x = 1, so\n\n       (x+y)(y+z) = x y + y^2 + y z + z x\n                    = (x y + y z + z x) + y^2\n                    = 1 + y^2.\n\n   Therefore\n\n       √\\frac{(1−a)(1−b)}{a b}\n       = √\\frac{1 + y^2}{y^2}\n       = \\frac{√{1 + y^2}}{y}.\n\n   Finally, setting y = tan(β/2) with 0<β<π, we have √{1+y^2}=1/|cos(β/2)|=1/cos(β/2) (since 0<β/2<π/2), and so\n\n       √\\frac{1+y^2}{y^2} = \\frac{1}{cos(β/2)·tan(β/2)} = \\frac{1}{sin(β/2)}.\n\n   In this way we obtain the key identities:\n\n       √\\bigl(1/a − 1\\bigr) · √\\bigl(1/b − 1\\bigr) = 1/\\sin(β/2),\n       √\\bigl(1/b − 1\\bigr) · √\\bigl(1/c − 1\\bigr) = 1/\\sin(γ/2),\n       √\\bigl(1/c − 1\\bigr) · √\\bigl(1/a − 1\\bigr) = 1/\\sin(α/2),\n\n   where we have likewise set x=tan(α/2), z=tan(γ/2), and imposed α+β+γ=π so that x y + y z + z x =1.\n\n3. Reduction to an inequality in half‐angles.  \n   The original sum becomes\n\n       S = \\frac1{\\sin(α/2)} + \\frac1{\\sin(β/2)} + \\frac1{\\sin(γ/2)}.\n\n   We wish to show S ≥ C for all positive α,β,γ with α+β+γ=π, and then find the maximal C.\n\n4. Applying the AM–HM inequality.  \n   Let u=sin(α/2), v=sin(β/2), w=sin(γ/2); then u,v,w>0 and u+v+w ≤ ? (we will bound this next).  The arithmetic mean–harmonic mean inequality for the three numbers 1/u,1/v,1/w states:\n\n       (1/u + 1/v + 1/w)/3 ≥ 3/(u + v + w).\n\n   Multiplying both sides by 3 gives\n\n       1/u + 1/v + 1/w ≥ 9/(u + v + w).\n\n   Hence\n\n       S ≥ 9/(sin(α/2) + sin(β/2) + sin(γ/2)).         (2)\n\n   To deduce a lower bound for S, it suffices to obtain an upper bound on sin(α/2)+sin(β/2)+sin(γ/2).\n\n5. Bounding the sum of sines via Jensen’s inequality.  \n   Note that the function f(t)=sin t is concave on the interval [0,π/2].  Since α/2,β/2,γ/2 ∈ (0,π/2) and\n\n       (α/2) + (β/2) + (γ/2) = π/2,\n\n   Jensen’s inequality for a concave function yields\n\n       [sin(α/2) + sin(β/2) + sin(γ/2)]/3  ≤  sin((α/2+β/2+γ/2)/3)\n                                      =  sin(π/6)\n                                      =  1/2.\n\n   Therefore\n\n       sin(α/2) + sin(β/2) + sin(γ/2)  ≤  3·(1/2)  =  3/2.        (3)\n\n6. Concluding the lower bound for S.  \n   Combining (2) and (3), we obtain\n\n       S ≥ 9/(sin(α/2)+sin(β/2)+sin(γ/2))  ≥  9/(3/2)  =  6.\n\n   Hence for all a,b,c>0 with a+b+c=1,\n\n       √\\bigl(1/a−1\\bigr)√\\bigl(1/b−1\\bigr) + √\\bigl(1/b−1\\bigr)√\\bigl(1/c−1\\bigr) + √\\bigl(1/c−1\\bigr)√\\bigl(1/a−1\\bigr)  ≥  6.\n\n7. Determining the maximal constant and the equality case.  \n   Equality in the AM–HM step requires u=v=w, i.e. sin(α/2)=sin(β/2)=sin(γ/2).  Combined with α/2+β/2+γ/2=π/2, this forces α/2=β/2=γ/2=π/6, so α=β=γ=π/3.\n   Then x=y=z=tan(π/6)=1/√3, whence a=xy=1/3, b=yz=1/3, c=zx=1/3.  In this symmetric case the sum S exactly equals 6, showing that\n\n       6\n\n   is indeed the largest constant C for which the inequality holds in full generality.\n\nTherefore, the answer is $C=6$.",
    "original_entry": {
        "data_id": "33",
        "problem": "Let $a, b, c$ be positive real numbers such that $a + b + c = 1$. Find the largest constant $C$ such that the following inequality holds for all $a, b, c$:\n$$\n\\sqrt{\\frac{1}{a}-1} \\sqrt{\\frac{1}{b}-1} + \\sqrt{\\frac{1}{b}-1} \\sqrt{\\frac{1}{c}-1} + \\sqrt{\\frac{1}{c}-1} \\sqrt{\\frac{1}{a}-1} \\geq C\n$$",
        "type": "bound",
        "data_split": "train",
        "answer": "$$C = 6$$",
        "solution": "Let $a=x y, b=y z, c=z x$. Then $x y+y z+z x=1$ and we may take\n$$\nx=\\tan \\frac{\\alpha}{2}, \\quad y=\\tan \\frac{\\beta}{2}, \\quad z=\\tan \\frac{\\gamma}{2}\n$$\nwhere $\\alpha, \\beta, \\gamma \\in(0, \\pi)$ and $\\alpha+\\beta+\\gamma=\\pi$.\nWe have\n$$\n\\begin{aligned}\n\\sqrt{\\frac{1}{a}-1} \\sqrt{\\frac{1}{b}-1} & =\\sqrt{\\frac{(1-a)(1-b)}{a b}}=\\sqrt{\\frac{(1-x y)(1-y z)}{x y^{2} z}} \\\\\n& =\\sqrt{\\frac{(y z+z x)(z x+x y)}{x y^{2} z}}=\\sqrt{\\frac{(y+x)(z+y)}{y^{2}}}=\\frac{\\sqrt{1+y^{2}}}{y} \\\\\n& =\\frac{\\sqrt{1+\\tan ^{2} \\frac{\\beta}{2}}}{\\tan \\frac{\\beta}{2}}=\\frac{1}{\\sin \\frac{\\beta}{2}}\n\\end{aligned}\n$$\n\nSimilarly we obtain\n$$\n\\sqrt{\\frac{1}{b}-1} \\sqrt{\\frac{1}{c}-1}=\\frac{1}{\\sin \\frac{\\gamma}{2}} \\quad \\text { and } \\quad \\sqrt{\\frac{1}{c}-1} \\sqrt{\\frac{1}{a}-1}=\\frac{1}{\\sin \\frac{\\alpha}{2}}\n$$\n\nNow the given inequality becomes\n$$\n\\frac{1}{\\sin \\frac{\\alpha}{2}}+\\frac{1}{\\sin \\frac{\\beta}{2}}+\\frac{1}{\\sin \\frac{\\gamma}{2}} \\geq 6\n$$\n\nBy $A M \\geq H M$ we have\n$$\n\\frac{1}{\\sin \\frac{\\alpha}{2}}+\\frac{1}{\\sin \\frac{\\beta}{2}}+\\frac{1}{\\sin \\frac{\\gamma}{2}} \\geq \\frac{9}{\\sin \\frac{\\alpha}{2}+\\sin \\frac{\\beta}{2}+\\sin \\frac{\\gamma}{2}}\n$$\n\nSo we need to prove that $\\sin \\frac{\\alpha}{2}+\\sin \\frac{\\beta}{2}+\\sin \\frac{\\gamma}{2} \\leq \\frac{3}{2}$.\n\nEquality occurs if and only if $\\alpha=\\beta=\\gamma=\\pi / 3$, i.e. $a=b=c=\\frac{1}{3}$. In this case, the minimum value of the expression is achieved, so $C = 6$ is the largest constant for which the inequality always holds.\n\nTherefore, the answer is $C = 6$.",
        "theorems": {
            "Theorem 35": {
                "Nickname": [
                    "mean inequalities"
                ],
                "Theorem": "Let $a_{1}, a_{2}, \\ldots, a_{n}$ be positive real numbers. The numbers\n$$\n\\begin{aligned}\n& Q M=\\sqrt{\\frac{a_{1}^{2}+a_{2}^{2}+\\cdots+a_{n}^{2}}{n}}, \\quad A M=\\frac{a_{1}+a_{2}+\\cdots+a_{n}}{n} \\\\\n& G M=\\sqrt[n]{a_{1} a_{2} \\cdots a_{n}} \\quad \\text { and } \\quad H M=\\frac{n}{\\frac{1}{a_{1}}+\\frac{1}{a_{2}}+\\cdots+\\frac{1}{a_{n}}}\n\\end{aligned}\n$$\nare called the quadratic, arithmetic, geometric and harmonic mean for the numbers $a_{1}, a_{2}, \\ldots, a_{n}$, respectively, and we have\n$$\nQ M \\geq A M \\geq G M \\geq H M\n$$\n\nEqualities occur if and only if $a_{1}=a_{2}=\\cdots=a_{n}$.",
                "Theorem_Category": "Inequality Between Means"
            }
        },
        "difficulty": ""
    }
}